{"is":"system","title":"lernsax_schullogin","permalink":"https://Schullogin.github.io/affected/lernsax_schullogin/","status":"ok","pages":[{"is":"issue","title":"Geplante Wartung Wartung im ZIH, mit Auswirkungen auf Dienste auf dem SBS","createdAt":"2022-09-21 19:10:00 +0000 UTC","lastMod":"2022-09-21 19:10:00 +0000 UTC","permalink":"https://Schullogin.github.io/issues/2022-09-21t1700--wartungsbszih/","severity":"<no value>","resolved":false,"informational":true,"resolvedAt":"<no value>","affected":["Anmeldung","Support","Schnittstellen","Nachrichten","Dateiablage","Videokonferenzen (BigBlueButton)","lernsax_schullogin","OPAL Schule","mesax_schullogin","EtherPad","Redaktionssystem","SchulCMS","E-Learning SBS-moodle","E-Mail-Übungsumgebung Minimehl","Cooperative Working BSCW","Cooperative Learning BSCL","FTP-Schulhomepages","Schul-wiki","Materialdatenbank","Geographisches Informationssystem WebGIS","Online Umfragetool","Eventplaner","Außerschulische Lernorte","Mailinglisten","Ticketsystem"],"filename":"2022-09-21T1700--WartungSBSZIH.md"},{"is":"issue","title":"SBS von Wartung im ZIH Betroffen","createdAt":"2022-09-19 19:10:00 +0000 UTC","lastMod":"2022-09-19 19:10:00 +0000 UTC","permalink":"https://Schullogin.github.io/issues/2022-09-19t2000--wartungsbs/","severity":"down","resolved":true,"informational":false,"resolvedAt":"2022-09-19T23:59:00","affected":["Anmeldung","Support","Schnittstellen","Nachrichten","Dateiablage","Videokonferenzen (BigBlueButton)","lernsax_schullogin","OPAL Schule","mesax_schullogin","EtherPad","Redaktionssystem","SchulCMS","E-Learning SBS-moodle","E-Mail-Übungsumgebung Minimehl","Cooperative Working BSCW","Cooperative Learning BSCL","FTP-Schulhomepages","Schul-wiki","Materialdatenbank","Geographisches Informationssystem WebGIS","Online Umfragetool","Eventplaner","Außerschulische Lernorte","Mailinglisten","Ticketsystem"],"filename":"2022-09-19T2000--WartungSBS.md"}]}