{"is":"issue","title":"Software-Update Core-Router TU Dresden (01.06.2023)","createdAt":"2023-06-01 17:00:00 +0000 UTC","lastMod":"2024-08-13 15:36:01 +0200 +0200","permalink":"https://Schullogin.github.io/issues/2023-06-01t1700--software-update_core-router_tu_dresden_01.06.2023/","severity":"<no value>","resolved":true,"informational":true,"resolvedAt":"2023-06-01T24:00:00","affected":["Anmeldung","Support","Schnittstellen","Nachrichten","Dateiablage","Videokonferenz","LernSax Schullogin","OPAL Schule","MeSax Schullogin","Etherpad","Redaktionssystem","SchulCMS","Moodle","E-Mail-Übungsumgebung Minimehl","Cooperative Working BSCW","Cooperative Learning BSCL","FTP-Schulhomepages","Schul-wiki","Materialdatenbank","Geographisches Informationssystem WebGIS","Online Umfragetool","Eventplaner","Außerschulische Lernorte","Mailinglisten","Ticketsystem"],"filename":"2023-06-01T1700--Software-Update_Core-Router_TU_Dresden_(01.06.2023).md"}