{"is":"issue","title":"Schullogin/SBS: Wartung Internetanbindung (09.05.2025, 16:00 - 18:00 Uhr)","body":"\u003cp\u003eDie beiden LZR-Backbone-Routern müssen aufgrund von notwendigen Konfigurationsänderungen zeitnah neugestartet werden. Davon sind auch die Server des SBS betroffen.\u003c/p\u003e\n\u003cp\u003eDie Neustarts erfolgen am Fr. 09.05.2025 16:00 - 18:00 Uhr.\u003c/p\u003e\n\u003cp\u003eDie Router sind jeweils als Paar ausgelegt \u0026amp; es wird immer nur einer der beiden Router in den Maintenance-Modus versetzt \u0026amp; neugestartet, sodass der andere weiterhin die Netzversorgung erbringt.\nEs kann sein, dass es beim Wiederzuschalten der TRE-Backbone-Router zu kurzen Unterbrechungen kommt - bitte richten Sie sich darauf ein!\u003c/p\u003e\n","createdAt":"2025-05-09 16:00:00 +0000 UTC","lastMod":"2025-05-14 08:36:43 +0000 UTC","permalink":"https://Schullogin.github.io/issues/2025-05-09t1600--wartung_internetanbindung_schullogin_und_dienste/","severity":"<no value>","resolved":false,"informational":true,"resolvedAt":"<no value>","affected":["Anmeldung","Support","Schnittstellen","Nachrichten","Dateiablage","LernSax Schullogin","MeSax Schullogin","Etherpad","Assistent KAI","Redaktionssystem","SchulCMS","Moodle","E-Mail-Übungsumgebung Minimehl","Cooperative Working BSCW","Cooperative Learning BSCL","FTP-Schulhomepages","Schul-wiki","Materialdatenbank","Geographisches Informationssystem WebGIS","Online Umfragetool","Eventplaner","Außerschulische Lernorte","Mailinglisten","Ticketsystem","GitLab"],"filename":"2025-05-09T1600--Wartung_Internetanbindung_Schullogin_und_Dienste.md"}