{"is":"issue","title":"Schullogin: Accountübersicht für Lehrkräfte nicht erreichbar (09.01.2025)","body":"\u003cp\u003eDie \u003ca href=\"https://docs.schullogin.de/15-Schnellstart/20-Accounts-verwalten/05-Nutzeruebersicht/Index.html\"\u003eAccountübersicht für Lehrkräfte\u003c/a\u003e ist aktuell nicht erreichbar.\u003c/p\u003e\n\u003cp\u003eDer Fehler ist bekannt und wird zeitnah behoben.\u003c/p\u003e\n","createdAt":"2025-01-09 08:00:00 +0000 UTC","lastMod":"2025-01-09 09:20:27 +0000 UTC","permalink":"https://Schullogin.github.io/issues/2025-01-09t0800--schullogin_accountuebersicht_fuer_lehrkraefte_nicht_erreichbar_09.01.2025/","severity":"disrupted","resolved":true,"informational":false,"resolvedAt":"2025-01-09T10:15:00","affected":["Support","Schnittstellen"],"filename":"2025-01-09T0800--Schullogin_Accountuebersicht_fuer_Lehrkraefte_nicht_erreichbar_(09.01.2025).md"}