{"is":"issue","title":"Videokonferenzen: Update auf Greenlight 3.6.3 am 29.08.2025","body":"\u003cp\u003eAm Freitag, dem 29.08.2025 updaten wir den Vermittlungsserver (\u0026ldquo;Greenlight\u0026rdquo;) unseres Videokonferenzdienstes BigBlueButton (BBB) auf Version 3.6.3. Es sollte dabei zu keinen Einschränkungen in der Nutzbarkeit kommen.\u003c/p\u003e\n\u003ch2 id=\"update\"\u003eUpdate\u003c/h2\u003e\n\u003cp\u003eDas Update wurde erfolgreich abgeschlossen.\u003c/p\u003e\n","createdAt":"2025-08-29 20:00:00 +0000 UTC","lastMod":"2025-09-12 23:03:48 +0200 +0200","permalink":"https://Schullogin.github.io/issues/2025-08-29t2000--update_bbb_vermittlungsserver/","severity":"<no value>","resolved":true,"informational":false,"resolvedAt":"2025-08-29T20:30:00","affected":["Videokonferenzen (BigBlueButton)"],"filename":"2025-08-29T2000--Update_BBB_Vermittlungsserver.md"}